<?xml version="1.0" encoding="UTF-8"?>
<report xmlns="http://www.eclipse.org/birt/2005/design" version="3.2.23" id="1">
    <property name="createdBy">Eclipse BIRT Designer Version 4.8.0.v201806261756</property>
    <property name="units">in</property>
    <property name="iconFile">/templates/blank_report.gif</property>
    <property name="bidiLayoutOrientation">ltr</property>
    <property name="imageDPI">96</property>
    <parameters>
        <scalar-parameter name="teacherId" id="6">
            <text-property name="promptText">Enter Teacher ID</text-property>
            <property name="valueType">static</property>
            <property name="dataType">string</property>
            <property name="distinct">true</property>
            <list-property name="selectionList"/>
            <property name="paramType">simple</property>
            <property name="controlType">text-box</property>
            <structure name="format">
                <property name="category">Unformatted</property>
            </structure>
        </scalar-parameter>
        <scalar-parameter name="instituteId" id="7">
            <text-property name="promptText">Enter Institute ID</text-property>
            <property name="valueType">static</property>
            <property name="dataType">string</property>
            <property name="distinct">true</property>
            <list-property name="selectionList"/>
            <property name="paramType">simple</property>
            <property name="controlType">text-box</property>
            <structure name="format">
                <property name="category">Unformatted</property>
            </structure>
        </scalar-parameter>
    </parameters>
    <data-sources>
        <oda-data-source extensionID="org.eclipse.birt.data.oda.pojo" name="TVW_TEACHER_ATTENDANCE_DETAIL" id="4">
            <list-property name="privateDriverProperties">
                <ex-property>
                    <name>SynchronizeClassPath</name>
                    <value>true</value>
                </ex-property>
                <ex-property>
                    <name>pojoClassPath</name>
                    <value>dataSource/CohesiveReportEngine-ejb.jar;</value>
                </ex-property>
            </list-property>
            <property name="pojoDataSetClassPath">dataSource/CohesiveReportEngine-ejb.jar;</property>
        </oda-data-source>
    </data-sources>
    <data-sets>
        <oda-data-set extensionID="org.eclipse.birt.data.oda.pojo.dataSet" name="TVW_TEACHER_ATTENDANCE_DETAIL" id="5">
            <list-property name="columnHints">
                <structure>
                    <property name="columnName">TEACHER_ID</property>
                    <text-property name="heading">TEACHER_ID</text-property>
                </structure>
                <structure>
                    <property name="columnName">DATE</property>
                    <text-property name="heading">DATE</text-property>
                </structure>
                <structure>
                    <property name="columnName">SUBJECT_ID</property>
                    <text-property name="heading">SUBJECT_ID</text-property>
                </structure>
                <structure>
                    <property name="columnName">STANDARD</property>
                    <text-property name="heading">STANDARD</text-property>
                </structure>
                <structure>
                    <property name="columnName">SECTION</property>
                    <text-property name="heading">SECTION</text-property>
                </structure>
                <structure>
                    <property name="columnName">PERIOD_NO</property>
                    <text-property name="heading">PERIOD_NO</text-property>
                </structure>
                <structure>
                    <property name="columnName">SIGNATURE</property>
                    <text-property name="heading">SIGNATURE</text-property>
                </structure>
                <structure>
                    <property name="columnName">VERSION_NUMBER</property>
                    <text-property name="heading">VERSION_NUMBER</text-property>
                </structure>
            </list-property>
            <structure name="cachedMetaData">
                <list-property name="resultSet">
                    <structure>
                        <property name="position">1</property>
                        <property name="name">TEACHER_ID</property>
                        <property name="dataType">string</property>
                    </structure>
                    <structure>
                        <property name="position">2</property>
                        <property name="name">DATE</property>
                        <property name="dataType">string</property>
                    </structure>
                    <structure>
                        <property name="position">3</property>
                        <property name="name">SUBJECT_ID</property>
                        <property name="dataType">string</property>
                    </structure>
                    <structure>
                        <property name="position">4</property>
                        <property name="name">STANDARD</property>
                        <property name="dataType">string</property>
                    </structure>
                    <structure>
                        <property name="position">5</property>
                        <property name="name">SECTION</property>
                        <property name="dataType">string</property>
                    </structure>
                    <structure>
                        <property name="position">6</property>
                        <property name="name">PERIOD_NO</property>
                        <property name="dataType">string</property>
                    </structure>
                    <structure>
                        <property name="position">7</property>
                        <property name="name">SIGNATURE</property>
                        <property name="dataType">string</property>
                    </structure>
                    <structure>
                        <property name="position">8</property>
                        <property name="name">VERSION_NUMBER</property>
                        <property name="dataType">string</property>
                    </structure>
                </list-property>
            </structure>
            <property name="dataSource">TVW_TEACHER_ATTENDANCE_DETAIL</property>
            <list-property name="resultSet">
                <structure>
                    <property name="position">1</property>
                    <property name="name">TEACHER_ID</property>
                    <property name="nativeName">TEACHER_ID</property>
                    <property name="dataType">string</property>
                    <property name="nativeDataType">1</property>
                </structure>
                <structure>
                    <property name="position">2</property>
                    <property name="name">DATE</property>
                    <property name="nativeName">DATE</property>
                    <property name="dataType">string</property>
                    <property name="nativeDataType">1</property>
                </structure>
                <structure>
                    <property name="position">3</property>
                    <property name="name">SUBJECT_ID</property>
                    <property name="nativeName">SUBJECT_ID</property>
                    <property name="dataType">string</property>
                    <property name="nativeDataType">1</property>
                </structure>
                <structure>
                    <property name="position">4</property>
                    <property name="name">STANDARD</property>
                    <property name="nativeName">STANDARD</property>
                    <property name="dataType">string</property>
                    <property name="nativeDataType">1</property>
                </structure>
                <structure>
                    <property name="position">5</property>
                    <property name="name">SECTION</property>
                    <property name="nativeName">SECTION</property>
                    <property name="dataType">string</property>
                    <property name="nativeDataType">1</property>
                </structure>
                <structure>
                    <property name="position">6</property>
                    <property name="name">PERIOD_NO</property>
                    <property name="nativeName">PERIOD_NO</property>
                    <property name="dataType">string</property>
                    <property name="nativeDataType">1</property>
                </structure>
                <structure>
                    <property name="position">7</property>
                    <property name="name">SIGNATURE</property>
                    <property name="nativeName">SIGNATURE</property>
                    <property name="dataType">string</property>
                    <property name="nativeDataType">1</property>
                </structure>
                <structure>
                    <property name="position">8</property>
                    <property name="name">VERSION_NUMBER</property>
                    <property name="nativeName">VERSION_NUMBER</property>
                    <property name="dataType">string</property>
                    <property name="nativeDataType">1</property>
                </structure>
            </list-property>
            <xml-property name="queryText"><![CDATA[<?xml version="1.0" encoding="UTF-8" standalone="no"?>
<PojoQuery appContextKey="APP_CONTEXT_KEY_TVW_TEACHER_ATTENDANCE_DETAIL" dataSetClass="com.ibd.cohesive.report.dbreport.dataSources.teacher.TVW_TEACHER_ATTENDANCE_DETAIL_DataSource" version="1.0">
    <ColumnMapping index="1" name="TEACHER_ID" odaDataType="String">
        <Method name="getTEACHER_ID"/>
    </ColumnMapping>
    <ColumnMapping index="2" name="DATE" odaDataType="String">
        <Method name="getDATE"/>
    </ColumnMapping>
    <ColumnMapping index="3" name="SUBJECT_ID" odaDataType="String">
        <Method name="getSUBJECT_ID"/>
    </ColumnMapping>
    <ColumnMapping index="4" name="STANDARD" odaDataType="String">
        <Method name="getSTANDARD"/>
    </ColumnMapping>
    <ColumnMapping index="5" name="SECTION" odaDataType="String">
        <Method name="getSECTION"/>
    </ColumnMapping>
    <ColumnMapping index="6" name="PERIOD_NO" odaDataType="String">
        <Method name="getPERIOD_NO"/>
    </ColumnMapping>
    <ColumnMapping index="7" name="SIGNATURE" odaDataType="String">
        <Method name="getSIGNATURE"/>
    </ColumnMapping>
    <ColumnMapping index="8" name="VERSION_NUMBER" odaDataType="String">
        <Method name="getVERSION_NUMBER"/>
    </ColumnMapping>
</PojoQuery>
]]></xml-property>
            <xml-property name="designerValues"><![CDATA[<?xml version="1.0" encoding="UTF-8"?>
<model:DesignValues xmlns:design="http://www.eclipse.org/datatools/connectivity/oda/design" xmlns:model="http://www.eclipse.org/birt/report/model/adapter/odaModel">
  <Version>2.0</Version>
  <design:ResultSets derivedMetaData="true">
    <design:resultSetDefinitions>
      <design:resultSetColumns>
        <design:resultColumnDefinitions>
          <design:attributes>
            <design:identifier>
              <design:name>TEACHER_ID</design:name>
              <design:position>1</design:position>
            </design:identifier>
            <design:nativeDataTypeCode>1</design:nativeDataTypeCode>
            <design:precision>-1</design:precision>
            <design:scale>-1</design:scale>
            <design:nullability>Unknown</design:nullability>
          </design:attributes>
          <design:usageHints>
            <design:label>TEACHER_ID</design:label>
            <design:formattingHints/>
          </design:usageHints>
        </design:resultColumnDefinitions>
        <design:resultColumnDefinitions>
          <design:attributes>
            <design:identifier>
              <design:name>DATE</design:name>
              <design:position>2</design:position>
            </design:identifier>
            <design:nativeDataTypeCode>1</design:nativeDataTypeCode>
            <design:precision>-1</design:precision>
            <design:scale>-1</design:scale>
            <design:nullability>Unknown</design:nullability>
          </design:attributes>
          <design:usageHints>
            <design:label>DATE</design:label>
            <design:formattingHints/>
          </design:usageHints>
        </design:resultColumnDefinitions>
        <design:resultColumnDefinitions>
          <design:attributes>
            <design:identifier>
              <design:name>SUBJECT_ID</design:name>
              <design:position>3</design:position>
            </design:identifier>
            <design:nativeDataTypeCode>1</design:nativeDataTypeCode>
            <design:precision>-1</design:precision>
            <design:scale>-1</design:scale>
            <design:nullability>Unknown</design:nullability>
          </design:attributes>
          <design:usageHints>
            <design:label>SUBJECT_ID</design:label>
            <design:formattingHints/>
          </design:usageHints>
        </design:resultColumnDefinitions>
        <design:resultColumnDefinitions>
          <design:attributes>
            <design:identifier>
              <design:name>STANDARD</design:name>
              <design:position>4</design:position>
            </design:identifier>
            <design:nativeDataTypeCode>1</design:nativeDataTypeCode>
            <design:precision>-1</design:precision>
            <design:scale>-1</design:scale>
            <design:nullability>Unknown</design:nullability>
          </design:attributes>
          <design:usageHints>
            <design:label>STANDARD</design:label>
            <design:formattingHints/>
          </design:usageHints>
        </design:resultColumnDefinitions>
        <design:resultColumnDefinitions>
          <design:attributes>
            <design:identifier>
              <design:name>SECTION</design:name>
              <design:position>5</design:position>
            </design:identifier>
            <design:nativeDataTypeCode>1</design:nativeDataTypeCode>
            <design:precision>-1</design:precision>
            <design:scale>-1</design:scale>
            <design:nullability>Unknown</design:nullability>
          </design:attributes>
          <design:usageHints>
            <design:label>SECTION</design:label>
            <design:formattingHints/>
          </design:usageHints>
        </design:resultColumnDefinitions>
        <design:resultColumnDefinitions>
          <design:attributes>
            <design:identifier>
              <design:name>PERIOD_NO</design:name>
              <design:position>6</design:position>
            </design:identifier>
            <design:nativeDataTypeCode>1</design:nativeDataTypeCode>
            <design:precision>-1</design:precision>
            <design:scale>-1</design:scale>
            <design:nullability>Unknown</design:nullability>
          </design:attributes>
          <design:usageHints>
            <design:label>PERIOD_NO</design:label>
            <design:formattingHints/>
          </design:usageHints>
        </design:resultColumnDefinitions>
        <design:resultColumnDefinitions>
          <design:attributes>
            <design:identifier>
              <design:name>SIGNATURE</design:name>
              <design:position>7</design:position>
            </design:identifier>
            <design:nativeDataTypeCode>1</design:nativeDataTypeCode>
            <design:precision>-1</design:precision>
            <design:scale>-1</design:scale>
            <design:nullability>Unknown</design:nullability>
          </design:attributes>
          <design:usageHints>
            <design:label>SIGNATURE</design:label>
            <design:formattingHints/>
          </design:usageHints>
        </design:resultColumnDefinitions>
        <design:resultColumnDefinitions>
          <design:attributes>
            <design:identifier>
              <design:name>VERSION_NUMBER</design:name>
              <design:position>8</design:position>
            </design:identifier>
            <design:nativeDataTypeCode>1</design:nativeDataTypeCode>
            <design:precision>-1</design:precision>
            <design:scale>-1</design:scale>
            <design:nullability>Unknown</design:nullability>
          </design:attributes>
          <design:usageHints>
            <design:label>VERSION_NUMBER</design:label>
            <design:formattingHints/>
          </design:usageHints>
        </design:resultColumnDefinitions>
      </design:resultSetColumns>
      <design:criteria/>
    </design:resultSetDefinitions>
  </design:ResultSets>
</model:DesignValues>]]></xml-property>
            <list-property name="privateDriverProperties">
                <ex-property>
                    <name>methodNameRegx</name>
                    <value>get*</value>
                </ex-property>
                <ex-property>
                    <name>pojoClass</name>
                    <value>com.ibd.cohesive.report.dbreport.dataModels.teacher.TVW_TEACHER_ATTENDANCE_DETAIL</value>
                </ex-property>
            </list-property>
        </oda-data-set>
    </data-sets>
    <page-setup>
        <simple-master-page name="Simple MasterPage" id="2">
            <page-footer>
                <text id="3">
                    <property name="contentType">html</property>
                    <text-property name="content"><![CDATA[<value-of>new Date()</value-of>]]></text-property>
                </text>
            </page-footer>
        </simple-master-page>
    </page-setup>
    <body>
        <grid id="8">
            <column id="9"/>
            <row id="10">
                <cell id="11">
                    <label id="18">
                        <property name="textAlign">center</property>
                        <text-property name="text">Table Report</text-property>
                    </label>
                </cell>
            </row>
            <row id="12">
                <cell id="13">
                    <text id="19">
                        <property name="contentType">html</property>
                        <text-property name="content"><![CDATA[<H6>Instance ID: <VALUE-OF>params["instituteId"].value</VALUE-OF></H6>
<BR>
<H6>File Name:   <VALUE-OF>params["teacherId"].value</VALUE-OF></H6>
<BR>
<H6>Table Name:  TVW_TEACHER_ATTENDANCE_DETAIL</H6><BR>
]]></text-property>
                    </text>
                </cell>
            </row>
            <row id="14">
                <cell id="15">
                    <table id="20">
                        <property name="dataSet">TVW_TEACHER_ATTENDANCE_DETAIL</property>
                        <list-property name="boundDataColumns">
                            <structure>
                                <property name="name">TEACHER_ID</property>
                                <text-property name="displayName">TEACHER_ID</text-property>
                                <expression name="expression" type="javascript">dataSetRow["TEACHER_ID"]</expression>
                                <property name="dataType">string</property>
                            </structure>
                            <structure>
                                <property name="name">DATE</property>
                                <text-property name="displayName">DATE</text-property>
                                <expression name="expression" type="javascript">dataSetRow["DATE"]</expression>
                                <property name="dataType">string</property>
                            </structure>
                            <structure>
                                <property name="name">SUBJECT_ID</property>
                                <text-property name="displayName">SUBJECT_ID</text-property>
                                <expression name="expression" type="javascript">dataSetRow["SUBJECT_ID"]</expression>
                                <property name="dataType">string</property>
                            </structure>
                            <structure>
                                <property name="name">STANDARD</property>
                                <text-property name="displayName">STANDARD</text-property>
                                <expression name="expression" type="javascript">dataSetRow["STANDARD"]</expression>
                                <property name="dataType">string</property>
                            </structure>
                            <structure>
                                <property name="name">SECTION</property>
                                <text-property name="displayName">SECTION</text-property>
                                <expression name="expression" type="javascript">dataSetRow["SECTION"]</expression>
                                <property name="dataType">string</property>
                            </structure>
                            <structure>
                                <property name="name">PERIOD_NO</property>
                                <text-property name="displayName">PERIOD_NO</text-property>
                                <expression name="expression" type="javascript">dataSetRow["PERIOD_NO"]</expression>
                                <property name="dataType">string</property>
                            </structure>
                            <structure>
                                <property name="name">SIGNATURE</property>
                                <text-property name="displayName">SIGNATURE</text-property>
                                <expression name="expression" type="javascript">dataSetRow["SIGNATURE"]</expression>
                                <property name="dataType">string</property>
                            </structure>
                            <structure>
                                <property name="name">VERSION_NUMBER</property>
                                <text-property name="displayName">VERSION_NUMBER</text-property>
                                <expression name="expression" type="javascript">dataSetRow["VERSION_NUMBER"]</expression>
                                <property name="dataType">string</property>
                            </structure>
                        </list-property>
                        <column id="64"/>
                        <column id="65"/>
                        <column id="66"/>
                        <column id="67"/>
                        <column id="68"/>
                        <column id="69"/>
                        <column id="70"/>
                        <column id="71"/>
                        <header>
                            <row id="21">
                                <cell id="22">
                                    <property name="borderBottomStyle">solid</property>
                                    <property name="borderBottomWidth">thin</property>
                                    <property name="borderLeftStyle">solid</property>
                                    <property name="borderLeftWidth">thin</property>
                                    <property name="borderRightStyle">solid</property>
                                    <property name="borderRightWidth">thin</property>
                                    <property name="borderTopStyle">solid</property>
                                    <property name="borderTopWidth">thin</property>
                                    <property name="textAlign">center</property>
                                    <label id="23">
                                        <text-property name="text">TEACHER_ID</text-property>
                                    </label>
                                </cell>
                                <cell id="24">
                                    <property name="borderBottomStyle">solid</property>
                                    <property name="borderBottomWidth">thin</property>
                                    <property name="borderLeftStyle">solid</property>
                                    <property name="borderLeftWidth">thin</property>
                                    <property name="borderRightStyle">solid</property>
                                    <property name="borderRightWidth">thin</property>
                                    <property name="borderTopStyle">solid</property>
                                    <property name="borderTopWidth">thin</property>
                                    <property name="textAlign">center</property>
                                    <label id="25">
                                        <text-property name="text">DATE</text-property>
                                    </label>
                                </cell>
                                <cell id="26">
                                    <property name="borderBottomStyle">solid</property>
                                    <property name="borderBottomWidth">thin</property>
                                    <property name="borderLeftStyle">solid</property>
                                    <property name="borderLeftWidth">thin</property>
                                    <property name="borderRightStyle">solid</property>
                                    <property name="borderRightWidth">thin</property>
                                    <property name="borderTopStyle">solid</property>
                                    <property name="borderTopWidth">thin</property>
                                    <property name="textAlign">center</property>
                                    <label id="27">
                                        <text-property name="text">SUBJECT_ID</text-property>
                                    </label>
                                </cell>
                                <cell id="28">
                                    <property name="borderBottomStyle">solid</property>
                                    <property name="borderBottomWidth">thin</property>
                                    <property name="borderLeftStyle">solid</property>
                                    <property name="borderLeftWidth">thin</property>
                                    <property name="borderRightStyle">solid</property>
                                    <property name="borderRightWidth">thin</property>
                                    <property name="borderTopStyle">solid</property>
                                    <property name="borderTopWidth">thin</property>
                                    <property name="textAlign">center</property>
                                    <label id="29">
                                        <text-property name="text">STANDARD</text-property>
                                    </label>
                                </cell>
                                <cell id="30">
                                    <property name="borderBottomStyle">solid</property>
                                    <property name="borderBottomWidth">thin</property>
                                    <property name="borderLeftStyle">solid</property>
                                    <property name="borderLeftWidth">thin</property>
                                    <property name="borderRightStyle">solid</property>
                                    <property name="borderRightWidth">thin</property>
                                    <property name="borderTopStyle">solid</property>
                                    <property name="borderTopWidth">thin</property>
                                    <property name="textAlign">center</property>
                                    <label id="31">
                                        <text-property name="text">SECTION</text-property>
                                    </label>
                                </cell>
                                <cell id="32">
                                    <property name="borderBottomStyle">solid</property>
                                    <property name="borderBottomWidth">thin</property>
                                    <property name="borderLeftStyle">solid</property>
                                    <property name="borderLeftWidth">thin</property>
                                    <property name="borderRightStyle">solid</property>
                                    <property name="borderRightWidth">thin</property>
                                    <property name="borderTopStyle">solid</property>
                                    <property name="borderTopWidth">thin</property>
                                    <property name="textAlign">center</property>
                                    <label id="33">
                                        <text-property name="text">PERIOD_NO</text-property>
                                    </label>
                                </cell>
                                <cell id="34">
                                    <property name="borderBottomStyle">solid</property>
                                    <property name="borderBottomWidth">thin</property>
                                    <property name="borderLeftStyle">solid</property>
                                    <property name="borderLeftWidth">thin</property>
                                    <property name="borderRightStyle">solid</property>
                                    <property name="borderRightWidth">thin</property>
                                    <property name="borderTopStyle">solid</property>
                                    <property name="borderTopWidth">thin</property>
                                    <property name="textAlign">center</property>
                                    <label id="35">
                                        <text-property name="text">SIGNATURE</text-property>
                                    </label>
                                </cell>
                                <cell id="36">
                                    <property name="borderBottomStyle">solid</property>
                                    <property name="borderBottomWidth">thin</property>
                                    <property name="borderLeftStyle">solid</property>
                                    <property name="borderLeftWidth">thin</property>
                                    <property name="borderRightStyle">solid</property>
                                    <property name="borderRightWidth">thin</property>
                                    <property name="borderTopStyle">solid</property>
                                    <property name="borderTopWidth">thin</property>
                                    <property name="textAlign">center</property>
                                    <label id="37">
                                        <text-property name="text">VERSION_NUMBER</text-property>
                                    </label>
                                </cell>
                            </row>
                        </header>
                        <detail>
                            <row id="38">
                                <cell id="39">
                                    <property name="borderBottomStyle">solid</property>
                                    <property name="borderBottomWidth">thin</property>
                                    <property name="borderLeftStyle">solid</property>
                                    <property name="borderLeftWidth">thin</property>
                                    <property name="borderRightStyle">solid</property>
                                    <property name="borderRightWidth">thin</property>
                                    <property name="borderTopStyle">solid</property>
                                    <property name="borderTopWidth">thin</property>
                                    <property name="textAlign">center</property>
                                    <data id="40">
                                        <property name="resultSetColumn">TEACHER_ID</property>
                                    </data>
                                </cell>
                                <cell id="41">
                                    <property name="borderBottomStyle">solid</property>
                                    <property name="borderBottomWidth">thin</property>
                                    <property name="borderLeftStyle">solid</property>
                                    <property name="borderLeftWidth">thin</property>
                                    <property name="borderRightStyle">solid</property>
                                    <property name="borderRightWidth">thin</property>
                                    <property name="borderTopStyle">solid</property>
                                    <property name="borderTopWidth">thin</property>
                                    <property name="textAlign">center</property>
                                    <data id="42">
                                        <property name="resultSetColumn">DATE</property>
                                    </data>
                                </cell>
                                <cell id="43">
                                    <property name="borderBottomStyle">solid</property>
                                    <property name="borderBottomWidth">thin</property>
                                    <property name="borderLeftStyle">solid</property>
                                    <property name="borderLeftWidth">thin</property>
                                    <property name="borderRightStyle">solid</property>
                                    <property name="borderRightWidth">thin</property>
                                    <property name="borderTopStyle">solid</property>
                                    <property name="borderTopWidth">thin</property>
                                    <property name="textAlign">center</property>
                                    <data id="44">
                                        <property name="resultSetColumn">SUBJECT_ID</property>
                                    </data>
                                </cell>
                                <cell id="45">
                                    <property name="borderBottomStyle">solid</property>
                                    <property name="borderBottomWidth">thin</property>
                                    <property name="borderLeftStyle">solid</property>
                                    <property name="borderLeftWidth">thin</property>
                                    <property name="borderRightStyle">solid</property>
                                    <property name="borderRightWidth">thin</property>
                                    <property name="borderTopStyle">solid</property>
                                    <property name="borderTopWidth">thin</property>
                                    <property name="textAlign">center</property>
                                    <data id="46">
                                        <property name="resultSetColumn">STANDARD</property>
                                    </data>
                                </cell>
                                <cell id="47">
                                    <property name="borderBottomStyle">solid</property>
                                    <property name="borderBottomWidth">thin</property>
                                    <property name="borderLeftStyle">solid</property>
                                    <property name="borderLeftWidth">thin</property>
                                    <property name="borderRightStyle">solid</property>
                                    <property name="borderRightWidth">thin</property>
                                    <property name="borderTopStyle">solid</property>
                                    <property name="borderTopWidth">thin</property>
                                    <property name="textAlign">center</property>
                                    <data id="48">
                                        <property name="resultSetColumn">SECTION</property>
                                    </data>
                                </cell>
                                <cell id="49">
                                    <property name="borderBottomStyle">solid</property>
                                    <property name="borderBottomWidth">thin</property>
                                    <property name="borderLeftStyle">solid</property>
                                    <property name="borderLeftWidth">thin</property>
                                    <property name="borderRightStyle">solid</property>
                                    <property name="borderRightWidth">thin</property>
                                    <property name="borderTopStyle">solid</property>
                                    <property name="borderTopWidth">thin</property>
                                    <property name="textAlign">center</property>
                                    <data id="50">
                                        <property name="resultSetColumn">PERIOD_NO</property>
                                    </data>
                                </cell>
                                <cell id="51">
                                    <property name="borderBottomStyle">solid</property>
                                    <property name="borderBottomWidth">thin</property>
                                    <property name="borderLeftStyle">solid</property>
                                    <property name="borderLeftWidth">thin</property>
                                    <property name="borderRightStyle">solid</property>
                                    <property name="borderRightWidth">thin</property>
                                    <property name="borderTopStyle">solid</property>
                                    <property name="borderTopWidth">thin</property>
                                    <property name="textAlign">center</property>
                                    <data id="52">
                                        <property name="resultSetColumn">SIGNATURE</property>
                                    </data>
                                </cell>
                                <cell id="53">
                                    <property name="borderBottomStyle">solid</property>
                                    <property name="borderBottomWidth">thin</property>
                                    <property name="borderLeftStyle">solid</property>
                                    <property name="borderLeftWidth">thin</property>
                                    <property name="borderRightStyle">solid</property>
                                    <property name="borderRightWidth">thin</property>
                                    <property name="borderTopStyle">solid</property>
                                    <property name="borderTopWidth">thin</property>
                                    <property name="textAlign">center</property>
                                    <data id="54">
                                        <property name="resultSetColumn">VERSION_NUMBER</property>
                                    </data>
                                </cell>
                            </row>
                        </detail>
                        <footer>
                            <row id="55">
                                <cell id="56">
                                    <property name="borderBottomStyle">solid</property>
                                    <property name="borderBottomWidth">thin</property>
                                    <property name="borderLeftStyle">solid</property>
                                    <property name="borderLeftWidth">thin</property>
                                    <property name="borderRightStyle">solid</property>
                                    <property name="borderRightWidth">thin</property>
                                    <property name="borderTopStyle">solid</property>
                                    <property name="borderTopWidth">thin</property>
                                    <property name="textAlign">center</property>
                                </cell>
                                <cell id="57">
                                    <property name="borderBottomStyle">solid</property>
                                    <property name="borderBottomWidth">thin</property>
                                    <property name="borderLeftStyle">solid</property>
                                    <property name="borderLeftWidth">thin</property>
                                    <property name="borderRightStyle">solid</property>
                                    <property name="borderRightWidth">thin</property>
                                    <property name="borderTopStyle">solid</property>
                                    <property name="borderTopWidth">thin</property>
                                    <property name="textAlign">center</property>
                                </cell>
                                <cell id="58">
                                    <property name="borderBottomStyle">solid</property>
                                    <property name="borderBottomWidth">thin</property>
                                    <property name="borderLeftStyle">solid</property>
                                    <property name="borderLeftWidth">thin</property>
                                    <property name="borderRightStyle">solid</property>
                                    <property name="borderRightWidth">thin</property>
                                    <property name="borderTopStyle">solid</property>
                                    <property name="borderTopWidth">thin</property>
                                    <property name="textAlign">center</property>
                                </cell>
                                <cell id="59">
                                    <property name="borderBottomStyle">solid</property>
                                    <property name="borderBottomWidth">thin</property>
                                    <property name="borderLeftStyle">solid</property>
                                    <property name="borderLeftWidth">thin</property>
                                    <property name="borderRightStyle">solid</property>
                                    <property name="borderRightWidth">thin</property>
                                    <property name="borderTopStyle">solid</property>
                                    <property name="borderTopWidth">thin</property>
                                    <property name="textAlign">center</property>
                                </cell>
                                <cell id="60">
                                    <property name="borderBottomStyle">solid</property>
                                    <property name="borderBottomWidth">thin</property>
                                    <property name="borderLeftStyle">solid</property>
                                    <property name="borderLeftWidth">thin</property>
                                    <property name="borderRightStyle">solid</property>
                                    <property name="borderRightWidth">thin</property>
                                    <property name="borderTopStyle">solid</property>
                                    <property name="borderTopWidth">thin</property>
                                    <property name="textAlign">center</property>
                                </cell>
                                <cell id="61">
                                    <property name="borderBottomStyle">solid</property>
                                    <property name="borderBottomWidth">thin</property>
                                    <property name="borderLeftStyle">solid</property>
                                    <property name="borderLeftWidth">thin</property>
                                    <property name="borderRightStyle">solid</property>
                                    <property name="borderRightWidth">thin</property>
                                    <property name="borderTopStyle">solid</property>
                                    <property name="borderTopWidth">thin</property>
                                    <property name="textAlign">center</property>
                                </cell>
                                <cell id="62">
                                    <property name="borderBottomStyle">solid</property>
                                    <property name="borderBottomWidth">thin</property>
                                    <property name="borderLeftStyle">solid</property>
                                    <property name="borderLeftWidth">thin</property>
                                    <property name="borderRightStyle">solid</property>
                                    <property name="borderRightWidth">thin</property>
                                    <property name="borderTopStyle">solid</property>
                                    <property name="borderTopWidth">thin</property>
                                    <property name="textAlign">center</property>
                                </cell>
                                <cell id="63">
                                    <property name="borderBottomStyle">solid</property>
                                    <property name="borderBottomWidth">thin</property>
                                    <property name="borderLeftStyle">solid</property>
                                    <property name="borderLeftWidth">thin</property>
                                    <property name="borderRightStyle">solid</property>
                                    <property name="borderRightWidth">thin</property>
                                    <property name="borderTopStyle">solid</property>
                                    <property name="borderTopWidth">thin</property>
                                    <property name="textAlign">center</property>
                                </cell>
                            </row>
                        </footer>
                    </table>
                </cell>
            </row>
            <row id="16">
                <cell id="17"/>
            </row>
        </grid>
    </body>
</report>
